comicbox/__init__.py
comicbox/box/__init__.py
comicbox/box/archive/__init__.py
comicbox/box/archive/archive.py
comicbox/box/archive/archiveinfo.py
comicbox/box/archive/filenames.py
comicbox/box/archive/init.py
comicbox/box/archive/mtime.py
comicbox/box/archive/pages.py
comicbox/box/archive/read.py
comicbox/box/archive/write.py
comicbox/box/computed/__init__.py
comicbox/box/computed/date.py
comicbox/box/computed/identifiers.py
comicbox/box/computed/issue.py
comicbox/box/computed/notes.py
comicbox/box/computed/pages.py
comicbox/box/computed/stamp.py
comicbox/box/computed/stories_title.py
comicbox/box/dump.py
comicbox/box/dump_files.py
comicbox/box/init.py
comicbox/box/load.py
comicbox/box/merge.py
comicbox/box/metadata.py
comicbox/box/normalize.py
comicbox/box/pages/__init__.py
comicbox/box/pages/covers.py
comicbox/box/pages/extract.py
comicbox/box/print.py
comicbox/box/sources.py
comicbox/box/types.py
comicbox/cli.py
comicbox/config/__init__.py
comicbox/config/computed.py
comicbox/config/formats.py
comicbox/config/frozenattrdict.py
comicbox/config/paths.py
comicbox/config/read.py
comicbox/config_default.yaml
comicbox/empty.py
comicbox/enums/__init__.py
comicbox/enums/comet.py
comicbox/enums/comicbookinfo.py
comicbox/enums/comicbox.py
comicbox/enums/comicinfo.py
comicbox/enums/generic/__init__.py
comicbox/enums/generic/age_rating.py
comicbox/enums/generic/role.py
comicbox/enums/maps/__init__.py
comicbox/enums/maps/age_rating.py
comicbox/enums/maps/formats.py
comicbox/enums/maps/identifiers.py
comicbox/enums/maps/reading_direction.py
comicbox/enums/maps/roles.py
comicbox/enums/metroninfo.py
comicbox/exceptions.py
comicbox/fields/__init__.py
comicbox/fields/collection_fields.py
comicbox/fields/comicbox.py
comicbox/fields/comicinfo.py
comicbox/fields/enum_fields.py
comicbox/fields/fields.py
comicbox/fields/metroninfo.py
comicbox/fields/number_fields.py
comicbox/fields/pdf.py
comicbox/fields/pycountry.py
comicbox/fields/time_fields.py
comicbox/fields/union.py
comicbox-2.1.1.dist-info/WHEEL
comicbox-2.1.1.dist-info/entry_points.txt
comicbox-2.1.1.dist-info/METADATA
comicbox-2.1.1.dist-info/RECORD
