Metadata-Version: 2.4
Name: comicbox
Version: 2.1.1
Summary: Comic book archive multi format metadata read/write/transform tool and image extractor.
Keywords: comic,cbz,cbr,cbt,cb7,pdf,comicinfo,comicbookinfo,comet,metroninfo
Author: AJ Slater
Author-email: AJ Slater <aj@slater.net>
License-Expression: LGPL-3.0-only
Classifier: Development Status :: 5 - Production/Stable
Classifier: Environment :: Console
Classifier: Intended Audience :: Developers
Classifier: License :: OSI Approved :: GNU Lesser General Public License v3 (LGPLv3)
Classifier: Operating System :: OS Independent
Classifier: Programming Language :: Python :: 3
Requires-Dist: ansicolors~=1.1.8
Requires-Dist: bidict~=0.23
Requires-Dist: case-converter~=1.2
Requires-Dist: confuse==2.1.0
Requires-Dist: comicfn2dict>=0.2.4,<1.0.0
Requires-Dist: deepdiff~=8.2
Requires-Dist: glom~=25.12
Requires-Dist: loguru~=0.7
Requires-Dist: marshmallow~=4.2.0
Requires-Dist: marshmallow-union>=0.1.15.post1
Requires-Dist: pycountry~=24.6
Requires-Dist: python-dateutil~=2.8
Requires-Dist: py7zr~=1.1.0
Requires-Dist: rarfile~=4.0
Requires-Dist: rich~=14.0
Requires-Dist: rich-argparse~=1.7
Requires-Dist: ruamel-yaml~=0.18
Requires-Dist: simplejson~=3.19
Requires-Dist: typing-extensions~=4.13
Requires-Dist: urnparse~=0.2
Requires-Dist: xmltodict~=1.0
Requires-Dist: zipremove~=0.1
Requires-Dist: comicbox-pdffile~=0.3 ; extra == 'pdf'
Requires-Python: >=3.10
Project-URL: Documentation, https://comicbox.readthedocs.io
Project-URL: News, https://comicbox.readthedocs.io/NEWS/
Project-URL: Source, https://github.com/ajslater/comicbox
Provides-Extra: pdf
